ai_transform/__init__.py
ai_transform/config.py
ai_transform/constants.py
ai_transform/errors.py
ai_transform/logger.py
ai_transform/timer.py
ai_transform/types.py
ai_transform/api/__init__.py
ai_transform/api/api.py
ai_transform/api/client.py
ai_transform/api/endpoints.py
ai_transform/api/helpers.py
ai_transform/api/wrappers.py
ai_transform/components/__init__.py
ai_transform/components/components.py
ai_transform/dataset/__init__.py
ai_transform/dataset/dataset.py
ai_transform/dataset/field.py
ai_transform/engine/__init__.py
ai_transform/engine/abstract_engine.py
ai_transform/engine/dense_output_engine.py
ai_transform/engine/in_memory_engine.py
ai_transform/engine/multipass_engine.py
ai_transform/engine/small_batch_stable_engine.py
ai_transform/engine/stable_engine.py
ai_transform/operator/__init__.py
ai_transform/operator/abstract_operator.py
ai_transform/operator/dense_operator.py
ai_transform/utils/__init__.py
ai_transform/utils/document.py
ai_transform/utils/document_list.py
ai_transform/utils/encode_parameters.py
ai_transform/utils/example_documents.py
ai_transform/utils/json_encoder.py
ai_transform/utils/keyphrase.py
ai_transform/workflow/__init__.py
ai_transform/workflow/abstract_workflow.py
ai_transform/workflow/context_manager.py
ai_transform/workflow/helpers.py
tests/__init__.py
tests/components.py
tests/conftest.py
tests/test_connection_retry.py
tests/core/__init__.py
tests/core/test_api/__init__.py
tests/core/test_api/test_client.py
tests/core/test_api/test_endpoints.py
tests/core/test_api/test_keyphrase.py
tests/core/test_api/test_wrappers.py
tests/core/test_dataset/__init__.py
tests/core/test_dataset/test_dataset.py
tests/core/test_dataset/test_field.py
tests/core/test_dataset/test_keyphrase.py
tests/core/test_engine/__init__.py
tests/core/test_engine/test_dense_output_engine.py
tests/core/test_engine/test_engine.py
tests/core/test_engine/test_engine_playground.py
tests/core/test_engine/test_multipass_engine.py
ai_transform-0.32.6.dist-info/LICENSE
ai_transform-0.32.6.dist-info/METADATA
ai_transform-0.32.6.dist-info/WHEEL
ai_transform-0.32.6.dist-info/top_level.txt
ai_transform-0.32.6.dist-info/RECORD
